pingdomcli/__init__.py
pingdomcli/pdcli.py
pingdomcli-0.3.0.dist-info/entry_points.txt
pingdomcli-0.3.0.dist-info/WHEEL
pingdomcli-0.3.0.dist-info/METADATA
pingdomcli-0.3.0.dist-info/RECORD
