Metadata-Version: 2.1
Name: pingdomcli
Version: 0.3.0
Summary: CLI to interact with Pingdom API
Author: Alex Kelly
Author-email: alex.kelly@franklin.edu
Requires-Python: >=3.10,<4.0
Classifier: Programming Language :: Python :: 3
Classifier: Programming Language :: Python :: 3.10
Requires-Dist: PyYAML (>=6.0,<7.0)
Requires-Dist: click (>=8.0.3,<9.0.0)
Requires-Dist: requests (>=2.27.1,<3.0.0)
Requires-Dist: rich (>=11.0.0,<12.0.0)
